certbot_vault/__init__.py
certbot_vault/vault.py
certbot_vault_installer-0.4.3.dist-info/LICENSE
certbot_vault_installer-0.4.3.dist-info/METADATA
certbot_vault_installer-0.4.3.dist-info/WHEEL
certbot_vault_installer-0.4.3.dist-info/entry_points.txt
certbot_vault_installer-0.4.3.dist-info/top_level.txt
certbot_vault_installer-0.4.3.dist-info/RECORD
