Metadata-Version: 2.1
Name: certbot-vault-installer
Version: 0.4.3
Summary: Certbot plugin for interaction with HashiCorp Vault
Home-page: https://github.com/D3DeFi/certbot-vault
Author: Dusan Matejka
Author-email: d3defi@gmail.com
License: License Apache 2
Platform: UNKNOWN
Classifier: License :: OSI Approved :: Apache Software License
License-File: LICENSE
Requires-Dist: certbot
Requires-Dist: hvac
